dxfwrite/__init__.py
dxfwrite/acadctb.py
dxfwrite/allplancfg.py
dxfwrite/base.py
dxfwrite/const.py
dxfwrite/curves.py
dxfwrite/dimlines.py
dxfwrite/drawing.py
dxfwrite/engine.py
dxfwrite/entities.py
dxfwrite/hdrvars.py
dxfwrite/helpers.py
dxfwrite/htmlcolors.py
dxfwrite/insert2.py
dxfwrite/mixins.py
dxfwrite/mtext.py
dxfwrite/rect.py
dxfwrite/sections.py
dxfwrite/std.py
dxfwrite/table.py
dxfwrite/tableentries.py
dxfwrite/tables.py
dxfwrite/ucs.py
dxfwrite/util.py
dxfwrite/vector2d.py
dxfwrite/vector3d.py
dxfwrite/algebra/__init__.py
dxfwrite/algebra/base.py
dxfwrite/algebra/bezier.py
dxfwrite/algebra/circle.py
dxfwrite/algebra/clothoid.py
dxfwrite/algebra/cspline.py
dxfwrite/algebra/ray.py
dxfwrite-1.2.2.dist-info/LICENSE.txt
dxfwrite-1.2.2.dist-info/METADATA
dxfwrite-1.2.2.dist-info/WHEEL
dxfwrite-1.2.2.dist-info/top_level.txt
dxfwrite-1.2.2.dist-info/RECORD
