Metadata-Version: 1.1
Name: dxfwrite
Version: 1.2.2
Summary: A Python library to create DXF R12 drawings.
Home-page: https://github.com/mozman/dxfwrite.git
Author: Manfred Moitzi
Author-email: me@mozman.at
License: MIT License
Download-URL: https://github.com/mozman/dxfwrite/releases
Keywords: DXF
Platform: OS Independent
Classifier: Development Status :: 7 - Inactive
Classifier: License :: OSI Approved :: MIT License
Classifier: Operating System :: OS Independent
Classifier: Programming Language :: Python :: 3
Classifier: Programming Language :: Python :: 3.6
Classifier: Programming Language :: Python :: 3.7
Classifier: Programming Language :: Python :: Implementation :: CPython
Classifier: Programming Language :: Python :: Implementation :: PyPy
Classifier: Intended Audience :: Developers
Classifier: Topic :: Software Development :: Libraries :: Python Modules
Provides: dxfwrite
